{"html":[{"name":"Cramer","info":"Sito web per risolvere sistemi di primo grado con il metodo di Cramer","pagina":"https:\/\/domenicopopolizio.github.io\/cramer\/","github":"https:\/\/github.com\/domenicopopolizio\/domenicopopolizio.github.io\/tree\/master\/cramer"},{"name":"Risolutore di fisica","info":"Sito web in FASE BETA per risolvere problemi scolastici nei laboratori di fisica.","pagina":"https:\/\/domenicopopolizio.github.io\/fisicautomatica\/","github":"https:\/\/github.com\/domenicopopolizio\/domenicopopolizio.github.io\/tree\/master\/fisicautomatica"},{"name":"Frameset example","info":"Progettino scolastico per esercitarsi con l'uso dei frameset in html4","pagina":"https:\/\/domenicopopolizio.github.io\/frameset\/","github":"https:\/\/github.com\/domenicopopolizio\/domenicopopolizio.github.io\/tree\/master\/frameset"},{"name":"Sfumatura Lineare Verticale","info":"Pagina realizzata a scuola per l'apprendimento del funzionamento delle sfumature su canvas, per funzionare la pagina utilizza html5 e javascript","pagina":"https:\/\/domenicopopolizio.github.io\/sfumatura_lineare_verticale\/","github":"https:\/\/github.com\/domenicopopolizio\/domenicopopolizio.github.io\/tree\/master\/sfumatura_lineare_verticale"},{"name":"Approfondimento sulla dinamica","info":"Pagina contentente una relazione di approfondimento su un problema di dianamica","pagina":"https:\/\/domenicopopolizio.github.io\/approfondimento_fisica\/","github":"https:\/\/github.com\/domenicopopolizio\/domenicopopolizio.github.io\/blob\/master\/approfondimento_fisica"},{"name":"Vocabolary test","info":"Pagina realizzata attraverso html5 e javasript&jquery, utile a testare l'apprendimento di diversi vocaboli in inglese. Non \u00e8 stata curata graficamente, ma potrei sistemarla in futuro anche sotto quest'ultimo aspetto.<br>Inoltre potrei anche aggiungere nuovi vocaboli sempre in uno o pi\u00f9 aggiornamenti futuri.","pagina":"https:\/\/domenicopopolizio.github.io\/vocaboli_inglese\/","github":"https:\/\/github.com\/domenicopopolizio\/domenicopopolizio.github.io\/tree\/master\/vocaboli_inglese"},{"name":"Esercizio con le ordered list","info":"Esercizio scolastico creato per imparare a utilizzare le oredered list con l'html5","pagina":"https:\/\/domenicopopolizio.github.io\/esercizio_ol","github":"https:\/\/github.com\/domenicopopolizio\/domenicopopolizio.github.io\/tree\/master\/esercizio_ol"}],"C":[{"name":"Triangolo dati i lati","info":"Programmino relizzato a scuola per avere informazioni di un triangolo dati i suoi lati","pagina":"https:\/\/github.com\/domenicopopolizio\/some_c_programs\/tree\/master\/calcoli_triangolo_dati_lati","github":"https:\/\/github.com\/domenicopopolizio\/some_c_programs\/tree\/master\/calcoli_triangolo_dati_lati"},{"name":"Equazioni di secondo grado","info":"Programma realizzato a scuola per risolvere equazioni di secondo grado con il C","pagina":"https:\/\/github.com\/domenicopopolizio\/some_c_programs\/tree\/master\/equazioni_di_secondo_grado","github":"https:\/\/github.com\/domenicopopolizio\/some_c_programs\/tree\/master\/equazioni_di_secondo_grado"}]}